nats_publish/__init__.py
nats_publish/client.py
nats_publish-0.1.3.dist-info/METADATA
nats_publish-0.1.3.dist-info/WHEEL
nats_publish-0.1.3.dist-info/top_level.txt
nats_publish-0.1.3.dist-info/zip-safe
nats_publish-0.1.3.dist-info/RECORD
