Metadata-Version: 2.1
Name: nats-publish
Version: 0.1.3
Summary: Minimal go-nats publisher package
Home-page: http://github.com/rhnvrm/nats-publish-py
Author: Rohan Verma
Author-email: hello@rohanverma.net
License: MIT
Platform: UNKNOWN
